can_i_park/__init__.py
can_i_park/__main__.py
can_i_park/cli.py
can_i_park/exporter.py
can_i_park/utils.py
can_i_park-0.3.0.dist-info/METADATA
can_i_park-0.3.0.dist-info/WHEEL
can_i_park-0.3.0.dist-info/entry_points.txt
can_i_park-0.3.0.dist-info/top_level.txt
can_i_park-0.3.0.dist-info/RECORD
