Metadata-Version: 2.4
Name: can-i-park
Version: 0.3.0
Summary: A CLI and exporter to fetch the status of parkings in Ghent
Author-email: Bram Oosterlynck <bram.oosterlynck@gmail.com>
Project-URL: Homepage, https://github.com/boosterl/can-i-park
Classifier: License :: OSI Approved :: GNU General Public License v3 (GPLv3)
Classifier: Intended Audience :: Developers
Classifier: Programming Language :: Python :: 3
Classifier: Programming Language :: Python :: 3.8
Classifier: Programming Language :: Python :: 3.9
Classifier: Programming Language :: Python :: 3.10
Classifier: Programming Language :: Python :: 3.11
Classifier: Programming Language :: Python :: 3.12
Classifier: Programming Language :: Python :: 3.13
Classifier: Programming Language :: Python :: 3.14
Requires-Dist: click>=8.3.1
Requires-Dist: prometheus_client>=0.24.0
Requires-Dist: requests>=2.32.5
Requires-Dist: shellrecharge>=0.1.26
Provides-Extra: test
Requires-Dist: pytest>=8.4.2; extra == "test"
